{
    "FECHA DE VENCIMIENTO": "5/10/2022",
    "FECHA EMISION": "11 03 2022",
    "RUT_EMISOR": "91.806.000-6",
    "NFOLIO": "12031049",
    "RUT_CLIENTE": "76.242.774-5",
    "Nro CLIENTE": "0010779286",
    "GIRO": "CONST EDIF USO RESID",
    "CODIGO": "CONST EDIF USO RESID",
    "ITEM/DETALLE": "CONST EDIF USO RESID",
    "CANTIDAD": "6.644",
    "PUNITARIO": "538,85",
    "VALOR PARCIAL": "3.580.111",
    "N DESPACHO": "2791161",
    "ORDEN DE COMPRA": "4500860949",
    "FECHA ORDEN DE COMPRA": "31/01/2022",
    "GUIA DE DESPACHO": "2791161",
    "FECHA GUIA DE DESPACHO": "11/03/2022",
    "TOTAL AFECTO": "3.580.111",
    "19 % IVA": "680.221",
    "MONTO TOTAL": "$ : 4.260.332",
    "VENCIMIENTO": "04-FEB-2022",
    "CARGO FIJO": "718",
    "CONSUMO AGUA": "718",
    "CONSUMO AGUA NO PUNTA": "$ 436,77",
    "SOBRECONSUMO": "$ 1.276,06",
    "RECOLECCION": "$ 341.76",
    "TRATAMIENTO": "$ 341.76",
    "INTERES DEUDA": "4",
    "LECTURA ACTUAL": "05-ENE-2022",
    "LECTURA ANTERIOR": "06-DIC-2021",
    "DIFERENCIAS DE LECTURAS": "0m3",
    "CONSUMO TOTAL": "m3",
    "PROXIMA LECTURA": "m3",
    "FACTOR DE COBRO PERIODO": "1.00",
    "LIMITE DE SOBRECONSUMO": "40 M3",
    "NUMERO DE MEDIDOR": "20099105",
    "ULTIMO PAGO": "$701",
    "CONSIDERAR MOVIMIENTOS": "13-01-2022",
    "corte o reposicion 1era instancia": "$ 4.644",
    "corte o reposicion 2era instancia": "$ 6.399",
    "PLANTA TRATAMIENTO": "La Farfana y Mapocho Trebal",
    "NETO": "607",
    "IVA 19%": "115",
    "TOTAL VENTA": "115",
    "monto no facturado": "115",
    "SALDO ANTERIOR": "(1)"
}